{
  "openapi": "3.0.1",
  "info": {
    "title": "OrderManagement.API",
    "version": "1.0"
  },
  "paths": {
    "/api/Cliente": {
      "get": {
        "tags": [
          "Cliente"
        ],
        "responses": {
          "200": {
            "description": "OK"
          }
        }
      },
      "post": {
        "tags": [
          "Cliente"
        ],
        "requestBody": {
          "content": {
            "application/json": {
              "schema": {
                "$ref": "#/components/schemas/Cliente"
              }
            },
            "text/json": {
              "schema": {
                "$ref": "#/components/schemas/Cliente"
              }
            },
            "application/*+json": {
              "schema": {
                "$ref": "#/components/schemas/Cliente"
              }
            }
          }
        },
        "responses": {
          "200": {
            "description": "OK"
          }
        }
      }
    },
    "/api/Cliente/{id}": {
      "get": {
        "tags": [
          "Cliente"
        ],
        "parameters": [
          {
            "name": "id",
            "in": "path",
            "required": true,
            "schema": {
              "type": "string",
              "format": "uuid"
            }
          }
        ],
        "responses": {
          "200": {
            "description": "OK"
          }
        }
      },
      "delete": {
        "tags": [
          "Cliente"
        ],
        "parameters": [
          {
            "name": "id",
            "in": "path",
            "required": true,
            "schema": {
              "type": "string",
              "format": "uuid"
            }
          }
        ],
        "responses": {
          "200": {
            "description": "OK"
          }
        }
      }
    },
    "/api/Produto": {
      "get": {
        "tags": [
          "Produto"
        ],
        "responses": {
          "200": {
            "description": "OK"
          }
        }
      },
      "post": {
        "tags": [
          "Produto"
        ],
        "requestBody": {
          "content": {
            "application/json": {
              "schema": {
                "$ref": "#/components/schemas/Produto"
              }
            },
            "text/json": {
              "schema": {
                "$ref": "#/components/schemas/Produto"
              }
            },
            "application/*+json": {
              "schema": {
                "$ref": "#/components/schemas/Produto"
              }
            }
          }
        },
        "responses": {
          "200": {
            "description": "OK"
          }
        }
      }
    },
    "/api/Produto/{id}": {
      "get": {
        "tags": [
          "Produto"
        ],
        "parameters": [
          {
            "name": "id",
            "in": "path",
            "required": true,
            "schema": {
              "type": "string",
              "format": "uuid"
            }
          }
        ],
        "responses": {
          "200": {
            "description": "OK"
          }
        }
      },
      "delete": {
        "tags": [
          "Produto"
        ],
        "parameters": [
          {
            "name": "id",
            "in": "path",
            "required": true,
            "schema": {
              "type": "string",
              "format": "uuid"
            }
          }
        ],
        "responses": {
          "200": {
            "description": "OK"
          }
        }
      }
    }
  },
  "components": {
    "schemas": {
      "Cliente": {
        "required": [
          "dataDeCadastro",
          "email",
          "id",
          "nome"
        ],
        "type": "object",
        "properties": {
          "id": {
            "type": "string",
            "format": "uuid"
          },
          "dataDeCadastro": {
            "type": "string",
            "format": "date-time"
          },
          "nome": {
            "minLength": 1,
            "type": "string"
          },
          "email": {
            "minLength": 1,
            "type": "string"
          },
          "telefone": {
            "type": "string",
            "nullable": true
          }
        },
        "additionalProperties": false
      },
      "Produto": {
        "required": [
          "dataDeCadastro",
          "id",
          "nome",
          "preco",
          "quantidadeDisponivel"
        ],
        "type": "object",
        "properties": {
          "id": {
            "type": "string",
            "format": "uuid"
          },
          "dataDeCadastro": {
            "type": "string",
            "format": "date-time"
          },
          "nome": {
            "minLength": 1,
            "type": "string"
          },
          "descricao": {
            "type": "string",
            "nullable": true
          },
          "preco": {
            "type": "number",
            "format": "double"
          },
          "quantidadeDisponivel": {
            "type": "integer",
            "format": "int32"
          }
        },
        "additionalProperties": false
      }
    }
  }
}